rhml_server/__init__.py
rhml_server/setup_db.py
rhml_server/Deploy/__init__.py
rhml_server/Deploy/__main__.py
rhml_server/Deploy/deploy_api.py
rhml_server/Deploy/model_cell.py
rhml_server/Deploy/helpers/__init__.py
rhml_server/Deploy/helpers/configuration.py
rhml_server/Deploy/helpers/db_record_to_dictionary.py
rhml_server/Deploy/helpers/deploy.py
rhml_server/Deploy/helpers/deploy_memory_storage.py
rhml_server/Deploy/helpers/get_models_list.py
rhml_server/Deploy/helpers/remove_model.py
rhml_server/Deploy/helpers/scan_folder.py
rhml_server-0.0.3.dist-info/LICENCE.txt
rhml_server-0.0.3.dist-info/METADATA
rhml_server-0.0.3.dist-info/WHEEL
rhml_server-0.0.3.dist-info/top_level.txt
rhml_server-0.0.3.dist-info/RECORD
